RISparser/__init__.py
RISparser/config.py
RISparser/parser.py
RISparser-0.4.4.dist-info/LICENSE
RISparser-0.4.4.dist-info/METADATA
RISparser-0.4.4.dist-info/WHEEL
RISparser-0.4.4.dist-info/top_level.txt
RISparser-0.4.4.dist-info/RECORD
