Metadata-Version: 2.1
Name: RISparser
Version: 0.4.4
Summary: Reads RIS files into dictionaries via a generator for large files
Home-page: https://github.com/mrtango/RISparser
Author: Maik Derstappen (MrTango)
Author-email: md@derico.de
License: GNU General Public License v2 (GPLv2)
Keywords: RIS parser bibliograph
Platform: UNKNOWN
Classifier: Development Status :: 3 - Alpha
Classifier: Intended Audience :: Developers
Classifier: Topic :: Software Development :: Build Tools
Classifier: License :: OSI Approved :: GNU General Public License v2 (GPLv2)
Classifier: Programming Language :: Python :: 2
Classifier: Programming Language :: Python :: 2.7
Classifier: Programming Language :: Python :: 3
Classifier: Programming Language :: Python :: 3.5
Classifier: Programming Language :: Python :: 3.6
Provides-Extra: dev
Requires-Dist: check-manifest ; extra == 'dev'
Requires-Dist: wheel ; extra == 'dev'
Provides-Extra: test
Requires-Dist: coverage ; extra == 'test'
Requires-Dist: pytest ; extra == 'test'
